mopidy_waitforinternet/__init__.py
mopidy_waitforinternet/ext.conf
mopidy_waitfortimesync/__init__.py
mopidy_waitfortimesync/ext.conf
Mopidy_WaitForInternet-0.2.1.dist-info/LICENSE
Mopidy_WaitForInternet-0.2.1.dist-info/METADATA
Mopidy_WaitForInternet-0.2.1.dist-info/WHEEL
Mopidy_WaitForInternet-0.2.1.dist-info/entry_points.txt
Mopidy_WaitForInternet-0.2.1.dist-info/top_level.txt
Mopidy_WaitForInternet-0.2.1.dist-info/RECORD
