Metadata-Version: 2.1
Name: Mopidy-WaitForInternet
Version: 0.2.1
Summary: Mopidy extension that waits for internet connection during early startup.
Home-page: https://github.com/DavisNT/mopidy-waitforinternet
Author: Davis Mosenkovs
Author-email: python-apps@dm.id.lv
License: Apache License, Version 2.0
Classifier: Environment :: No Input/Output (Daemon)
Classifier: Intended Audience :: End Users/Desktop
Classifier: License :: OSI Approved :: Apache Software License
Classifier: Operating System :: OS Independent
Classifier: Programming Language :: Python :: 3
Classifier: Topic :: Multimedia :: Sound/Audio :: Players
Requires-Python: >= 3.7
License-File: LICENSE
Requires-Dist: setuptools
Requires-Dist: requests
Requires-Dist: Mopidy (>=3.0)
